elemelek/__init__.py
elemelek/db.py
elemelek/features.py
elemelek/genetic.py
elemelek/index.py
elemelek/logging.py
elemelek/model.py
elemelek/nest.py
elemelek/settings.py
elemelek/utils.py
elemelek-0.1.1.dist-info/METADATA
elemelek-0.1.1.dist-info/WHEEL
elemelek-0.1.1.dist-info/RECORD
