Metadata-Version: 2.1
Name: elemelek
Version: 0.1.1
Summary: Elemelek is designed to sample subsets of instructions gathered/generated from various sources (and so with various quality/diversity) for LLM fine-tuning tasks.
License: MIT
Author: int8
Requires-Python: >=3.9,<4.0
Classifier: License :: OSI Approved :: MIT License
Classifier: Programming Language :: Python :: 3
Classifier: Programming Language :: Python :: 3.9
Classifier: Programming Language :: Python :: 3.10
Classifier: Programming Language :: Python :: 3.11
Classifier: Programming Language :: Python :: 3.12
Requires-Dist: coloredlogs (>=15.0.1,<16.0.0)
Requires-Dist: jsonlines (>=4.0.0,<5.0.0)
Requires-Dist: language-tool-python (>=2.8,<3.0)
Requires-Dist: pandas (>=2.2.2,<3.0.0)
Requires-Dist: python-dotenv (>=1.0.1,<2.0.0)
Requires-Dist: pyyaml (>=6.0.1,<7.0.0)
Requires-Dist: sentence-transformers (>=2.7.0,<3.0.0)
Requires-Dist: tqdm (>=4.66.2,<5.0.0)
Requires-Dist: usearch (>=2.12,<3.0)
